Metadata-Version: 1.0
Name: django-textbin
Version: 0.433
Summary: Django package for text sharing and exchanging
Home-page: https://github.com/zokalo/django-textbin
Author: Don Dmitriy Sergeevich
Author-email: dondmitriys@gmail.com
License: GPL v3.0
Platform: UNKNOWN
